{"taller":"Taller Ramos y Ramos","cliente":{"nombre":"Arturo Ramos","vehiculo":"75076","orden":"OT-260330-002","nota":"Diagnóstico completado. Los repuestos marcados como Críticos son necesarios para la seguridad y correcto funcionamiento del vehículo. Los marcados como Recomendados presentan desgaste considerable. Los Opcionales pueden esperar pero se sugiere atenderlos próximamente."},"repuestos":[{"nombre":"Foco delantero derecho","cantidad":1,"prioridad":"Crítico","nota":"Esta espichado","_np":"5168484","origen":"usa","opciones":[{"calidad":"Original","estado":"Nuevo","marca":"Mercedes Benz","garantia":"","origen":"usa","precioFinalCRC":270270},{"calidad":"Original","estado":"Usado","marca":"Mercedes Benz","garantia":"","origen":"europa","precioFinalCRC":241313},{"calidad":"Genérico","estado":"Nuevo","marca":"","garantia":"","origen":"usa","precioFinalCRC":135281},{"calidad":"Alternativo","estado":"Nuevo","marca":"Vaico","garantia":"","origen":"usa","precioFinalCRC":483259}]}]}