{"taller":"Taller Ramos y Ramos","cliente":{"nombre":"Bernal Chavarria","vehiculo":"GBD678","orden":"OT-260417-003","nota":"","vin":"WDB2200701A138355"},"repuestos":[{"nombre":"Varilla de nivel de aceite de motor","cantidad":1,"prioridad":"Recomendado","nota":"","_np":"A1130100072","origen":"usa","opciones":[{"calidad":"Original","estado":"Nuevo","marca":"Mercedes Benz","garantia":"","origen":"usa","precioFinalCRC":43349},{"calidad":"Genérico","estado":"Nuevo","marca":"","garantia":"","origen":"usa","precioFinalCRC":28128}]}]}